DockerJiaochengCYuyanBianchengWang/README.md
DockerJiaochengCYuyanBianchengWang/__init__.py
DockerJiaochengCYuyanBianchengWang/__main__.py
DockerJiaochengCYuyanBianchengWang/file.epub
DockerJiaochengCYuyanBianchengWang/index.html
DockerJiaochengCYuyanBianchengWang/css/__init__.py
DockerJiaochengCYuyanBianchengWang/css/annotations.css
DockerJiaochengCYuyanBianchengWang/css/main.css
DockerJiaochengCYuyanBianchengWang/css/normalize.css
DockerJiaochengCYuyanBianchengWang/css/popup.css
DockerJiaochengCYuyanBianchengWang/font/__init__.py
DockerJiaochengCYuyanBianchengWang/font/fontello.eot
DockerJiaochengCYuyanBianchengWang/font/fontello.svg
DockerJiaochengCYuyanBianchengWang/font/fontello.ttf
DockerJiaochengCYuyanBianchengWang/font/fontello.woff
DockerJiaochengCYuyanBianchengWang/img/__init__.py
DockerJiaochengCYuyanBianchengWang/img/annotator-glyph-sprite.png
DockerJiaochengCYuyanBianchengWang/img/annotator-icon-sprite.png
DockerJiaochengCYuyanBianchengWang/img/apple-touch-icon.png
DockerJiaochengCYuyanBianchengWang/img/cancelfullscreen.png
DockerJiaochengCYuyanBianchengWang/img/close.png
DockerJiaochengCYuyanBianchengWang/img/fullscreen.png
DockerJiaochengCYuyanBianchengWang/img/loader.gif
DockerJiaochengCYuyanBianchengWang/img/menu-icon.png
DockerJiaochengCYuyanBianchengWang/img/save.png
DockerJiaochengCYuyanBianchengWang/img/saved.png
DockerJiaochengCYuyanBianchengWang/img/settings-s.png
DockerJiaochengCYuyanBianchengWang/img/settings.png
DockerJiaochengCYuyanBianchengWang/img/star.png
DockerJiaochengCYuyanBianchengWang/js/__init__.py
DockerJiaochengCYuyanBianchengWang/js/epub.js
DockerJiaochengCYuyanBianchengWang/js/epub.min.js
DockerJiaochengCYuyanBianchengWang/js/epub.min.map
DockerJiaochengCYuyanBianchengWang/js/hooks.min.js
DockerJiaochengCYuyanBianchengWang/js/hooks.min.map
DockerJiaochengCYuyanBianchengWang/js/reader.js
DockerJiaochengCYuyanBianchengWang/js/reader.js.map
DockerJiaochengCYuyanBianchengWang/js/reader.min.js
docker_jiaocheng_c_yuyan_biancheng_wang-2024.3.5.0.dist-info/METADATA
docker_jiaocheng_c_yuyan_biancheng_wang-2024.3.5.0.dist-info/WHEEL
docker_jiaocheng_c_yuyan_biancheng_wang-2024.3.5.0.dist-info/entry_points.txt
docker_jiaocheng_c_yuyan_biancheng_wang-2024.3.5.0.dist-info/top_level.txt
docker_jiaocheng_c_yuyan_biancheng_wang-2024.3.5.0.dist-info/RECORD
